attribution/__init__.py
attribution/shapley_attribution_ads.py
attribution/shapley_attribution_formula.py
shapley_attribution_wf/__init__.py
shapley_attribution_wf/shapley_attribution_ads.py
shapley_attribution_wf/shapley_attribution_formula.py
shapley_attribution_wf-0.0.12.dist-info/LICENSE
shapley_attribution_wf-0.0.12.dist-info/METADATA
shapley_attribution_wf-0.0.12.dist-info/WHEEL
shapley_attribution_wf-0.0.12.dist-info/top_level.txt
shapley_attribution_wf-0.0.12.dist-info/RECORD
